.gitignore
CHANGES.rst
README.rst
setup.py
src/collective/__init__.py
src/collective.chimpfeed.egg-info/PKG-INFO
src/collective.chimpfeed.egg-info/SOURCES.txt
src/collective.chimpfeed.egg-info/dependency_links.txt
src/collective.chimpfeed.egg-info/entry_points.txt
src/collective.chimpfeed.egg-info/namespace_packages.txt
src/collective.chimpfeed.egg-info/not-zip-safe
src/collective.chimpfeed.egg-info/requires.txt
src/collective.chimpfeed.egg-info/top_level.txt
src/collective/chimpfeed/__init__.py
src/collective/chimpfeed/api.py
src/collective/chimpfeed/campaign.pt
src/collective/chimpfeed/campaign.py
src/collective/chimpfeed/configure.zcml
src/collective/chimpfeed/controlpanel.pt
src/collective/chimpfeed/controlpanel.py
src/collective/chimpfeed/feed.pt.xml
src/collective/chimpfeed/feeds.py
src/collective/chimpfeed/form.py
src/collective/chimpfeed/interests.pt
src/collective/chimpfeed/interfaces.py
src/collective/chimpfeed/legacy.py
src/collective/chimpfeed/moderate.pt
src/collective/chimpfeed/newsletter.py
src/collective/chimpfeed/permissions.py
src/collective/chimpfeed/portlet.pt
src/collective/chimpfeed/portlet.py
src/collective/chimpfeed/preview.pt
src/collective/chimpfeed/schema.py
src/collective/chimpfeed/select.js
src/collective/chimpfeed/settings.py
src/collective/chimpfeed/setuphandlers.py
src/collective/chimpfeed/splitters.py
src/collective/chimpfeed/tests.py
src/collective/chimpfeed/upgradesteps.py
src/collective/chimpfeed/upgradesteps.zcml
src/collective/chimpfeed/urls.pt
src/collective/chimpfeed/vocabularies.py
src/collective/chimpfeed/locales/collective.chimpfeed.pot
src/collective/chimpfeed/locales/plone.pot
src/collective/chimpfeed/locales/da/LC_MESSAGES/collective.chimpfeed.po
src/collective/chimpfeed/locales/da/LC_MESSAGES/plone.po
src/collective/chimpfeed/names/da/female.txt
src/collective/chimpfeed/names/da/male.txt
src/collective/chimpfeed/profiles/default/actionicons.xml
src/collective/chimpfeed/profiles/default/browserlayer.xml
src/collective/chimpfeed/profiles/default/collective.chimpfeed.txt
src/collective/chimpfeed/profiles/default/componentregistry.xml
src/collective/chimpfeed/profiles/default/controlpanel.xml
src/collective/chimpfeed/profiles/default/import_steps.xml
src/collective/chimpfeed/profiles/default/metadata.xml
src/collective/chimpfeed/profiles/default/portlets.xml
