Metadata-Version: 1.1
Name: collective.chimpfeed
Version: 2.0
Summary: MailChimp-integration for Plone!
Home-page: UNKNOWN
Author: Malthe Borch
Author-email: mborch@gmail.com
License: GPL
Keywords: plone rss mailchimp
Platform: UNKNOWN
Classifier: Framework :: Plone
Classifier: Framework :: Zope2
Classifier: Programming Language :: Python
